botgus
