Metadata-Version: 2.1
Name: botgus
Version: 4.5
Summary: INDICADORES DE BOT GUS / 19 INDICADORES EN PYTHON
Home-page: https://github.com/jrchico/botgus
Author: Francisco Alas
Author-email: admin@botgus.com
Classifier: Programming Language :: Python :: 3
Classifier: License :: OSI Approved :: MIT License
Classifier: Operating System :: OS Independent
Requires-Python: >=3.6
